zuper_utils_soup.cpython-310-aarch64-linux-gnu.so
zuper_utils_soup.pyi
zuper_utils_soup_z7-7.3.2201261049.dist-info/METADATA
zuper_utils_soup_z7-7.3.2201261049.dist-info/WHEEL
zuper_utils_soup_z7-7.3.2201261049.dist-info/top_level.txt
zuper_utils_soup_z7-7.3.2201261049.dist-info/zip-safe
zuper_utils_soup_z7-7.3.2201261049.dist-info/RECORD
